v4l2.py
v4l2_fix-0.3.dist-info/AUTHORS
v4l2_fix-0.3.dist-info/LICENSE
v4l2_fix-0.3.dist-info/METADATA
v4l2_fix-0.3.dist-info/WHEEL
v4l2_fix-0.3.dist-info/top_level.txt
v4l2_fix-0.3.dist-info/RECORD
