Metadata-Version: 1.2
Name: v4l2-fix
Version: 0.3
Summary: Python bindings for the v4l2 userspace api.
Home-page: http://pypi.python.org/pypi/v4l2
Author: python-v4l2-devel
Author-email: 
Maintainer: ArduCam
Maintainer-email: ArduCam <support@arducam.com>
License: GPLv2
Keywords: v4l2 video4linux video4linux2 binding ctypes
Platform: UNKNOWN
Classifier: Development Status :: 4 - Beta
Classifier: Intended Audience :: Developers
Classifier: License :: OSI Approved :: GNU General Public License (GPL)
Classifier: Operating System :: POSIX :: Linux
Classifier: Programming Language :: C
Classifier: Programming Language :: Python
Classifier: Topic :: Multimedia :: Video
Classifier: Topic :: Multimedia :: Video :: Capture
Requires: ctypes
